md2slack/__init__.py
md2slack/grammar.py
md2slack/lexer.py
md2slack/parser.py
md2slack/renderer.py
md2slack-0.1.2.6.dist-info/licenses/LICENSE
md2slack-0.1.2.6.dist-info/METADATA
md2slack-0.1.2.6.dist-info/WHEEL
md2slack-0.1.2.6.dist-info/top_level.txt
md2slack-0.1.2.6.dist-info/RECORD
