Metadata-Version: 2.4
Name: md2Slack
Version: 0.1.2.6
Summary: Convert Markdown to Slack-friendly format.
Author: Eric Andersson
License-Expression: MIT
Requires-Python: >=3.6
License-File: LICENSE
Dynamic: license-file
